enchant_python_client/__init__.py
enchant_python_client/api/__init__.py
enchant_python_client/api/attachments/__init__.py
enchant_python_client/api/attachments/create_attachment.py
enchant_python_client/api/attachments/get_attachment.py
enchant_python_client/api/contacts/__init__.py
enchant_python_client/api/contacts/create_contact.py
enchant_python_client/api/contacts/delete_contact.py
enchant_python_client/api/customers/__init__.py
enchant_python_client/api/customers/create_customer.py
enchant_python_client/api/customers/get_customer.py
enchant_python_client/api/customers/list_customers.py
enchant_python_client/api/customers/update_customer.py
enchant_python_client/api/messages/__init__.py
enchant_python_client/api/messages/create_message.py
enchant_python_client/api/tickets/__init__.py
enchant_python_client/api/tickets/add_labels_to_ticket.py
enchant_python_client/api/tickets/create_ticket.py
enchant_python_client/api/tickets/get_ticket.py
enchant_python_client/api/tickets/list_tickets.py
enchant_python_client/api/tickets/remove_labels_from_ticket.py
enchant_python_client/api/tickets/update_ticket.py
enchant_python_client/api/users/__init__.py
enchant_python_client/api/users/list_users.py
enchant_python_client/client.py
enchant_python_client/errors.py
enchant_python_client/models/__init__.py
enchant_python_client/models/attachment.py
enchant_python_client/models/attachment_create.py
enchant_python_client/models/contact.py
enchant_python_client/models/contact_input.py
enchant_python_client/models/contact_type.py
enchant_python_client/models/create_attachment_xhttp_method_override.py
enchant_python_client/models/create_contact_xhttp_method_override.py
enchant_python_client/models/create_message_xhttp_method_override.py
enchant_python_client/models/create_ticket_xhttp_method_override.py
enchant_python_client/models/customer.py
enchant_python_client/models/customer_input.py
enchant_python_client/models/envelope.py
enchant_python_client/models/envelope_headers.py
enchant_python_client-1.0.0.dist-info/WHEEL
enchant_python_client-1.0.0.dist-info/METADATA
enchant_python_client-1.0.0.dist-info/RECORD
