Metadata-Version: 2.3
Name: enchant-python-client
Version: 1.0.0
Summary: A client library for accessing Enchant REST API
Keywords: enchant,api,client,helpdesk,customer-support,tickets
Author: Alfredo Ruiz
Author-email: Alfredo Ruiz <alfredo@globalvoice.mx>
License: MIT
Classifier: Development Status :: 4 - Beta
Classifier: Intended Audience :: Developers
Classifier: License :: OSI Approved :: MIT License
Classifier: Programming Language :: Python :: 3
Classifier: Programming Language :: Python :: 3.9
Classifier: Programming Language :: Python :: 3.10
Classifier: Programming Language :: Python :: 3.11
Classifier: Programming Language :: Python :: 3.12
Classifier: Topic :: Software Development :: Libraries :: Python Modules
Classifier: Topic :: Communications :: Email
Requires-Dist: httpx>=0.23.0,<0.29.0
Requires-Dist: attrs>=22.2.0
Requires-Dist: python-dateutil>=2.8.0,<3
Requires-Python: ~=3.9
Project-URL: Changelog, https://github.com/0x0a1f-stacc/enchant-python-client/blob/main/CHANGELOG.md
Project-URL: Documentation, https://github.com/0x0a1f-stacc/enchant-python-client/blob/main/README.md
Project-URL: Homepage, https://github.com/0x0a1f-stacc/enchant-python-client
Project-URL: Issues, https://github.com/0x0a1f-stacc/enchant-python-client/issues
Project-URL: Repository, https://github.com/0x0a1f-stacc/enchant-python-client
